autoai_ts_libs/__init__.py
autoai_ts_libs/version.cp312-win_amd64.pyd
autoai_ts_libs/anomaly_detection/__init__.py
autoai_ts_libs/anomaly_detection/estimators/__init__.py
autoai_ts_libs/anomaly_detection/estimators/constants.cp312-win_amd64.pyd
autoai_ts_libs/anomaly_detection/estimators/api/__init__.py
autoai_ts_libs/anomaly_detection/estimators/api/base.cp312-win_amd64.pyd
autoai_ts_libs/anomaly_detection/estimators/utils/__init__.py
autoai_ts_libs/anomaly_detection/estimators/utils/data_helper.cp312-win_amd64.pyd
autoai_ts_libs/anomaly_detection/estimators/utils/prediction_types.cp312-win_amd64.pyd
autoai_ts_libs/anomaly_detection/estimators/utils/watson_ts_utils.cp312-win_amd64.pyd
autoai_ts_libs/anomaly_detection/estimators/utils/wf_ad_utils.cp312-win_amd64.pyd
autoai_ts_libs/anomaly_detection/estimators/watfore/__init__.py
autoai_ts_libs/anomaly_detection/estimators/watfore/pointwise_bounded_ad.cp312-win_amd64.pyd
autoai_ts_libs/anomaly_detection/estimators/watfore/pointwise_forecasting_ad.cp312-win_amd64.pyd
autoai_ts_libs/anomaly_detection/estimators/watfore/window_ad.cp312-win_amd64.pyd
autoai_ts_libs/anomaly_detection/estimators/watfore/window_residual_ad.cp312-win_amd64.pyd
autoai_ts_libs/anomaly_detection/estimators/watson_ts/__init__.py
autoai_ts_libs/anomaly_detection/estimators/watson_ts/pred_ad/__init__.py
autoai_ts_libs/anomaly_detection/estimators/watson_ts/pred_ad/_bagging_ad.cp312-win_amd64.pyd
autoai_ts_libs/anomaly_detection/estimators/watson_ts/pred_ad/_base.cp312-win_amd64.pyd
autoai_ts_libs/anomaly_detection/estimators/watson_ts/pred_ad/_mt2r_forecaster_ad.cp312-win_amd64.pyd
autoai_ts_libs/anomaly_detection/estimators/watson_ts/pred_ad/_random_forest_ad.cp312-win_amd64.pyd
autoai_ts_libs/anomaly_detection/estimators/watson_ts/pred_ad/_t2r_forecaster_ad.cp312-win_amd64.pyd
autoai_ts_libs/anomaly_detection/estimators/watson_ts/pred_ad/_xgb_ad.cp312-win_amd64.pyd
autoai_ts_libs-5.0.5.dist-info/licenses/licenses/LA_cs
autoai_ts_libs-5.0.5.dist-info/licenses/licenses/LA_de
autoai_ts_libs-5.0.5.dist-info/licenses/licenses/LA_el
autoai_ts_libs-5.0.5.dist-info/licenses/licenses/LA_en
autoai_ts_libs-5.0.5.dist-info/licenses/licenses/LA_es
autoai_ts_libs-5.0.5.dist-info/licenses/licenses/LA_fr
autoai_ts_libs-5.0.5.dist-info/licenses/licenses/LA_in
autoai_ts_libs-5.0.5.dist-info/licenses/licenses/LA_it
autoai_ts_libs-5.0.5.dist-info/licenses/licenses/LA_ja
autoai_ts_libs-5.0.5.dist-info/licenses/licenses/LA_ko
autoai_ts_libs-5.0.5.dist-info/licenses/licenses/LA_lt
autoai_ts_libs-5.0.5.dist-info/licenses/licenses/LA_pl
autoai_ts_libs-5.0.5.dist-info/licenses/licenses/LA_pt
autoai_ts_libs-5.0.5.dist-info/licenses/licenses/LA_ru
autoai_ts_libs-5.0.5.dist-info/licenses/licenses/LA_sl
autoai_ts_libs-5.0.5.dist-info/licenses/licenses/LA_tr
autoai_ts_libs-5.0.5.dist-info/licenses/licenses/LA_zh
autoai_ts_libs-5.0.5.dist-info/licenses/licenses/LA_zh_TW
autoai_ts_libs-5.0.5.dist-info/licenses/licenses/LI_cs
autoai_ts_libs-5.0.5.dist-info/licenses/licenses/LI_de
autoai_ts_libs-5.0.5.dist-info/licenses/licenses/LI_el
autoai_ts_libs-5.0.5.dist-info/licenses/licenses/LI_en
autoai_ts_libs-5.0.5.dist-info/licenses/licenses/LI_es
autoai_ts_libs-5.0.5.dist-info/licenses/licenses/LI_fr
autoai_ts_libs-5.0.5.dist-info/licenses/licenses/LI_in
autoai_ts_libs-5.0.5.dist-info/licenses/licenses/LI_it
autoai_ts_libs-5.0.5.dist-info/licenses/licenses/LI_ja
autoai_ts_libs-5.0.5.dist-info/licenses/licenses/LI_ko
autoai_ts_libs-5.0.5.dist-info/licenses/licenses/LI_lt
autoai_ts_libs-5.0.5.dist-info/licenses/licenses/LI_pl
autoai_ts_libs-5.0.5.dist-info/licenses/licenses/LI_pt
autoai_ts_libs-5.0.5.dist-info/licenses/licenses/LI_ru
autoai_ts_libs-5.0.5.dist-info/licenses/licenses/LI_sl
autoai_ts_libs-5.0.5.dist-info/licenses/licenses/LI_tr
autoai_ts_libs-5.0.5.dist-info/licenses/licenses/LI_zh
autoai_ts_libs-5.0.5.dist-info/licenses/licenses/LI_zh_TW
autoai_ts_libs-5.0.5.dist-info/METADATA
autoai_ts_libs-5.0.5.dist-info/WHEEL
autoai_ts_libs-5.0.5.dist-info/top_level.txt
autoai_ts_libs-5.0.5.dist-info/RECORD
