Metadata-Version: 2.4
Name: autoai_ts_libs
Version: 5.0.5
Summary: A library of transformers to support portable representations of AutoAI TimeSeries pipelines.
Author: IBM
Maintainer-email: Łukasz Ćmielowski <lukasz.cmielowski@pl.ibm.com>, Marta Tomzik <marta.tomzik@ibm.com>
License: LICENSE INFORMATION
Keywords: AI,Watson,IBM,AutoAI,SDK,API,IBM Cloud,Machine Learning
Classifier: Development Status :: 5 - Production/Stable
Classifier: Natural Language :: English
Classifier: Programming Language :: Python :: 3.12
Classifier: Operating System :: MacOS :: MacOS X
Classifier: Operating System :: Microsoft :: Windows
Classifier: Operating System :: POSIX :: Linux
Classifier: Intended Audience :: Science/Research
Classifier: Intended Audience :: Developers
Classifier: Intended Audience :: Information Technology
Classifier: License :: Other/Proprietary License
Classifier: Topic :: Software Development :: Libraries
Classifier: Topic :: Software Development :: Libraries :: Python Modules
Classifier: Topic :: Scientific/Engineering :: Artificial Intelligence
Requires-Python: ~=3.12
License-File: licenses/LA_cs
License-File: licenses/LA_de
License-File: licenses/LA_el
License-File: licenses/LA_en
License-File: licenses/LA_es
License-File: licenses/LA_fr
License-File: licenses/LA_in
License-File: licenses/LA_it
License-File: licenses/LA_ja
License-File: licenses/LA_ko
License-File: licenses/LA_lt
License-File: licenses/LA_pl
License-File: licenses/LA_pt
License-File: licenses/LA_ru
License-File: licenses/LA_sl
License-File: licenses/LA_tr
License-File: licenses/LA_zh
License-File: licenses/LA_zh_TW
License-File: licenses/LI_cs
License-File: licenses/LI_de
License-File: licenses/LI_el
License-File: licenses/LI_en
License-File: licenses/LI_es
License-File: licenses/LI_fr
License-File: licenses/LI_in
License-File: licenses/LI_it
License-File: licenses/LI_ja
License-File: licenses/LI_ko
License-File: licenses/LI_lt
License-File: licenses/LI_pl
License-File: licenses/LI_pt
License-File: licenses/LI_ru
License-File: licenses/LI_sl
License-File: licenses/LI_tr
License-File: licenses/LI_zh
License-File: licenses/LI_zh_TW
Requires-Dist: alchemy-config<1.2,>=1.1.3
Requires-Dist: alchemy-logging<1.6,>=1.5.0
Requires-Dist: anytree<2.13,>=2.12.1
Requires-Dist: boto3<2.0.0
Requires-Dist: dill<0.5,>=0.3.1.1
Requires-Dist: ijson<3.4,>=3.1.0
Requires-Dist: import-tracker
Requires-Dist: joblib<1.5,>=1.4.2
Requires-Dist: jpype1<1.6,>=1.5.0
Requires-Dist: jsons<1.4.0,>=1.3.0
Requires-Dist: matplotlib
Requires-Dist: munch
Requires-Dist: networkx<3.5,>=3.2.1
Requires-Dist: numpy<2.1,>=2.0.2
Requires-Dist: lale<0.10,>=0.9
Requires-Dist: pandas<2.3,>=2.2.3
Requires-Dist: protobuf
Requires-Dist: PyWavelets
Requires-Dist: requests
Requires-Dist: scikit-learn<1.7,>=1.6.1
Requires-Dist: scipy<1.16,>=1.15.1
Requires-Dist: semver
Requires-Dist: six
Requires-Dist: statsmodels==0.14.*
Requires-Dist: tqdm<5.0.0
Requires-Dist: wrapt<1.18,>=1.17.2
Requires-Dist: xgboost<2.2,>=2.1.3
Requires-Dist: lightgbm<4.6,>=4.5
Provides-Extra: dev
Requires-Dist: autoai_ts_libs[test]; extra == "dev"
Requires-Dist: autoai_ts_libs[code-check]; extra == "dev"
Provides-Extra: test
Requires-Dist: pytest<8.0.0; extra == "test"
Requires-Dist: openpyxl; extra == "test"
Provides-Extra: code-check
Requires-Dist: black; extra == "code-check"
Dynamic: license-file
